<?xml version='1.0' encoding='utf-8'?>
<annotation verified="no">
	<folder>./JPEGImages</folder>
	<filename>1579</filename>
	<path>./JPEGImages\1579.jpg</path>
	<checked>NO</checked>
	<source>
		<database>Unknown</database>
	</source>
	<size>
		<width>1920</width>
		<height>1080</height>
		<depth>3</depth>
	</size>
	<segmented>0</segmented>
	<object>
		<name>ship</name>
		<flag>rectangle</flag>
		<pose>Unspecified</pose>
		<truncated>0</truncated>
		<difficult>0</difficult>
		<bndbox>
			<xmin>1893</xmin>
			<ymin>866</ymin>
			<xmax>1920</xmax>
			<ymax>895</ymax>
		</bndbox>
	</object>
	<object>
		<name>ship</name>
		<flag>rectangle</flag>
		<pose>Unspecified</pose>
		<truncated>0</truncated>
		<difficult>0</difficult>
		<bndbox>
			<xmin>202</xmin>
			<ymin>8</ymin>
			<xmax>498</xmax>
			<ymax>112</ymax>
		</bndbox>
	</object>
	<object>
		<name>ship</name>
		<flag>rectangle</flag>
		<pose>Unspecified</pose>
		<truncated>0</truncated>
		<difficult>0</difficult>
		<bndbox>
			<xmin>1446</xmin>
			<ymin>0</ymin>
			<xmax>1656</xmax>
			<ymax>28</ymax>
		</bndbox>
	</object>
	<object>
		<name>ship</name>
		<flag>rectangle</flag>
		<pose>Unspecified</pose>
		<truncated>0</truncated>
		<difficult>0</difficult>
		<bndbox>
			<xmin>805</xmin>
			<ymin>605</ymin>
			<xmax>922</xmax>
			<ymax>661</ymax>
		</bndbox>
	</object>
	<object>
		<name>ship</name>
		<flag>rectangle</flag>
		<pose>Unspecified</pose>
		<truncated>0</truncated>
		<difficult>0</difficult>
		<bndbox>
			<xmin>1777</xmin>
			<ymin>739</ymin>
			<xmax>1906</xmax>
			<ymax>778</ymax>
		</bndbox>
	</object>
	<object>
		<name>ship</name>
		<flag>rectangle</flag>
		<pose>Unspecified</pose>
		<truncated>0</truncated>
		<difficult>0</difficult>
		<bndbox>
			<xmin>1430</xmin>
			<ymin>622</ymin>
			<xmax>1564</xmax>
			<ymax>664</ymax>
		</bndbox>
	</object>
	<object>
		<name>ship</name>
		<flag>rectangle</flag>
		<pose>Unspecified</pose>
		<truncated>0</truncated>
		<difficult>0</difficult>
		<bndbox>
			<xmin>289</xmin>
			<ymin>507</ymin>
			<xmax>401</xmax>
			<ymax>541</ymax>
		</bndbox>
	</object>
	<object>
		<name>ship</name>
		<flag>rectangle</flag>
		<pose>Unspecified</pose>
		<truncated>0</truncated>
		<difficult>0</difficult>
		<bndbox>
			<xmin>522</xmin>
			<ymin>635</ymin>
			<xmax>669</xmax>
			<ymax>678</ymax>
		</bndbox>
	</object>
	<object>
		<name>ship</name>
		<flag>rectangle</flag>
		<pose>Unspecified</pose>
		<truncated>0</truncated>
		<difficult>0</difficult>
		<bndbox>
			<xmin>1047</xmin>
			<ymin>284</ymin>
			<xmax>1425</xmax>
			<ymax>388</ymax>
		</bndbox>
	</object>
	<object>
		<name>ship</name>
		<flag>rectangle</flag>
		<pose>Unspecified</pose>
		<truncated>0</truncated>
		<difficult>0</difficult>
		<bndbox>
			<xmin>604</xmin>
			<ymin>465</ymin>
			<xmax>763</xmax>
			<ymax>509</ymax>
		</bndbox>
	</object>
	<object>
		<name>ship</name>
		<flag>rectangle</flag>
		<pose>Unspecified</pose>
		<truncated>0</truncated>
		<difficult>0</difficult>
		<bndbox>
			<xmin>1215</xmin>
			<ymin>707</ymin>
			<xmax>1365</xmax>
			<ymax>747</ymax>
		</bndbox>
	</object>
</annotation>
