<?xml version='1.0' encoding='utf-8'?>
<annotation verified="no">
	<folder>./JPEGImages</folder>
	<filename>3015</filename>
	<path>./JPEGImages\3015.jpg</path>
	<checked>NO</checked>
	<source>
		<database>Unknown</database>
	</source>
	<size>
		<width>1920</width>
		<height>1080</height>
		<depth>3</depth>
	</size>
	<segmented>0</segmented>
	<object>
		<name>ship</name>
		<flag>rectangle</flag>
		<pose>Unspecified</pose>
		<truncated>0</truncated>
		<difficult>0</difficult>
		<bndbox>
			<xmin>391</xmin>
			<ymin>908</ymin>
			<xmax>575</xmax>
			<ymax>949</ymax>
		</bndbox>
	</object>
	<object>
		<name>ship</name>
		<flag>rectangle</flag>
		<pose>Unspecified</pose>
		<truncated>0</truncated>
		<difficult>0</difficult>
		<bndbox>
			<xmin>1270</xmin>
			<ymin>893</ymin>
			<xmax>1441</xmax>
			<ymax>930</ymax>
		</bndbox>
	</object>
	<object>
		<name>ship</name>
		<flag>rectangle</flag>
		<pose>Unspecified</pose>
		<truncated>0</truncated>
		<difficult>0</difficult>
		<bndbox>
			<xmin>111</xmin>
			<ymin>766</ymin>
			<xmax>267</xmax>
			<ymax>803</ymax>
		</bndbox>
	</object>
	<object>
		<name>ship</name>
		<flag>rectangle</flag>
		<pose>Unspecified</pose>
		<truncated>0</truncated>
		<difficult>0</difficult>
		<bndbox>
			<xmin>1632</xmin>
			<ymin>758</ymin>
			<xmax>1787</xmax>
			<ymax>803</ymax>
		</bndbox>
	</object>
	<object>
		<name>ship</name>
		<flag>rectangle</flag>
		<pose>Unspecified</pose>
		<truncated>0</truncated>
		<difficult>0</difficult>
		<bndbox>
			<xmin>570</xmin>
			<ymin>626</ymin>
			<xmax>785</xmax>
			<ymax>676</ymax>
		</bndbox>
	</object>
	<object>
		<name>ship</name>
		<flag>rectangle</flag>
		<pose>Unspecified</pose>
		<truncated>0</truncated>
		<difficult>0</difficult>
		<bndbox>
			<xmin>839</xmin>
			<ymin>941</ymin>
			<xmax>989</xmax>
			<ymax>995</ymax>
		</bndbox>
	</object>
	<object>
		<name>ship</name>
		<flag>rectangle</flag>
		<pose>Unspecified</pose>
		<truncated>0</truncated>
		<difficult>0</difficult>
		<bndbox>
			<xmin>1224</xmin>
			<ymin>200</ymin>
			<xmax>1787</xmax>
			<ymax>343</ymax>
		</bndbox>
	</object>
</annotation>
