<?xml version='1.0' encoding='utf-8'?>
<annotation verified="no">
	<folder>./JPEGImages</folder>
	<filename>805</filename>
	<path>./JPEGImages\805.jpg</path>
	<checked>NO</checked>
	<source>
		<database>Unknown</database>
	</source>
	<size>
		<width>1920</width>
		<height>1080</height>
		<depth>3</depth>
	</size>
	<segmented>0</segmented>
	<object>
		<name>ship</name>
		<flag>rectangle</flag>
		<pose>Unspecified</pose>
		<truncated>0</truncated>
		<difficult>0</difficult>
		<bndbox>
			<xmin>108</xmin>
			<ymin>456</ymin>
			<xmax>150</xmax>
			<ymax>467</ymax>
		</bndbox>
	</object>
	<object>
		<name>ship</name>
		<flag>rectangle</flag>
		<pose>Unspecified</pose>
		<truncated>0</truncated>
		<difficult>0</difficult>
		<bndbox>
			<xmin>1548</xmin>
			<ymin>472</ymin>
			<xmax>1604</xmax>
			<ymax>481</ymax>
		</bndbox>
	</object>
	<object>
		<name>ship</name>
		<flag>rectangle</flag>
		<pose>Unspecified</pose>
		<truncated>0</truncated>
		<difficult>0</difficult>
		<bndbox>
			<xmin>89</xmin>
			<ymin>885</ymin>
			<xmax>163</xmax>
			<ymax>908</ymax>
		</bndbox>
	</object>
	<object>
		<name>ship</name>
		<flag>rectangle</flag>
		<pose>Unspecified</pose>
		<truncated>0</truncated>
		<difficult>0</difficult>
		<bndbox>
			<xmin>0</xmin>
			<ymin>645</ymin>
			<xmax>78</xmax>
			<ymax>707</ymax>
		</bndbox>
	</object>
	<object>
		<name>ship</name>
		<flag>rectangle</flag>
		<pose>Unspecified</pose>
		<truncated>0</truncated>
		<difficult>0</difficult>
		<bndbox>
			<xmin>1784</xmin>
			<ymin>595</ymin>
			<xmax>1918</xmax>
			<ymax>623</ymax>
		</bndbox>
	</object>
	<object>
		<name>ship</name>
		<flag>rectangle</flag>
		<pose>Unspecified</pose>
		<truncated>0</truncated>
		<difficult>0</difficult>
		<bndbox>
			<xmin>1579</xmin>
			<ymin>951</ymin>
			<xmax>1718</xmax>
			<ymax>985</ymax>
		</bndbox>
	</object>
	<object>
		<name>ship</name>
		<flag>rectangle</flag>
		<pose>Unspecified</pose>
		<truncated>0</truncated>
		<difficult>0</difficult>
		<bndbox>
			<xmin>1429</xmin>
			<ymin>1013</ymin>
			<xmax>1587</xmax>
			<ymax>1052</ymax>
		</bndbox>
	</object>
	<object>
		<name>ship</name>
		<flag>rectangle</flag>
		<pose>Unspecified</pose>
		<truncated>0</truncated>
		<difficult>0</difficult>
		<bndbox>
			<xmin>421</xmin>
			<ymin>491</ymin>
			<xmax>548</xmax>
			<ymax>525</ymax>
		</bndbox>
	</object>
	<object>
		<name>ship</name>
		<flag>rectangle</flag>
		<pose>Unspecified</pose>
		<truncated>0</truncated>
		<difficult>0</difficult>
		<bndbox>
			<xmin>515</xmin>
			<ymin>874</ymin>
			<xmax>617</xmax>
			<ymax>900</ymax>
		</bndbox>
	</object>
	<object>
		<name>ship</name>
		<flag>rectangle</flag>
		<pose>Unspecified</pose>
		<truncated>0</truncated>
		<difficult>0</difficult>
		<bndbox>
			<xmin>778</xmin>
			<ymin>846</ymin>
			<xmax>922</xmax>
			<ymax>883</ymax>
		</bndbox>
	</object>
	<object>
		<name>ship</name>
		<flag>rectangle</flag>
		<pose>Unspecified</pose>
		<truncated>0</truncated>
		<difficult>0</difficult>
		<bndbox>
			<xmin>984</xmin>
			<ymin>926</ymin>
			<xmax>1100</xmax>
			<ymax>965</ymax>
		</bndbox>
	</object>
	<object>
		<name>ship</name>
		<flag>rectangle</flag>
		<pose>Unspecified</pose>
		<truncated>0</truncated>
		<difficult>0</difficult>
		<bndbox>
			<xmin>1156</xmin>
			<ymin>708</ymin>
			<xmax>1500</xmax>
			<ymax>805</ymax>
		</bndbox>
	</object>
	<object>
		<name>ship</name>
		<flag>rectangle</flag>
		<pose>Unspecified</pose>
		<truncated>0</truncated>
		<difficult>0</difficult>
		<bndbox>
			<xmin>758</xmin>
			<ymin>963</ymin>
			<xmax>905</xmax>
			<ymax>998</ymax>
		</bndbox>
	</object>
	<object>
		<name>ship</name>
		<flag>rectangle</flag>
		<pose>Unspecified</pose>
		<truncated>0</truncated>
		<difficult>0</difficult>
		<bndbox>
			<xmin>464</xmin>
			<ymin>584</ymin>
			<xmax>675</xmax>
			<ymax>652</ymax>
		</bndbox>
	</object>
</annotation>
