<?xml version='1.0' encoding='utf-8'?>
<annotation verified="no">
	<folder>./JPEGImages</folder>
	<filename>884</filename>
	<path>./JPEGImages\884.jpg</path>
	<checked>NO</checked>
	<source>
		<database>Unknown</database>
	</source>
	<size>
		<width>1920</width>
		<height>1080</height>
		<depth>3</depth>
	</size>
	<segmented>0</segmented>
	<object>
		<name>ship</name>
		<flag>rectangle</flag>
		<pose>Unspecified</pose>
		<truncated>0</truncated>
		<difficult>0</difficult>
		<bndbox>
			<xmin>672</xmin>
			<ymin>454</ymin>
			<xmax>707</xmax>
			<ymax>460</ymax>
		</bndbox>
	</object>
	<object>
		<name>ship</name>
		<flag>rectangle</flag>
		<pose>Unspecified</pose>
		<truncated>0</truncated>
		<difficult>0</difficult>
		<bndbox>
			<xmin>71</xmin>
			<ymin>464</ymin>
			<xmax>110</xmax>
			<ymax>477</ymax>
		</bndbox>
	</object>
	<object>
		<name>ship</name>
		<flag>rectangle</flag>
		<pose>Unspecified</pose>
		<truncated>0</truncated>
		<difficult>0</difficult>
		<bndbox>
			<xmin>1</xmin>
			<ymin>685</ymin>
			<xmax>34</xmax>
			<ymax>731</ymax>
		</bndbox>
	</object>
	<object>
		<name>ship</name>
		<flag>rectangle</flag>
		<pose>Unspecified</pose>
		<truncated>0</truncated>
		<difficult>0</difficult>
		<bndbox>
			<xmin>1511</xmin>
			<ymin>484</ymin>
			<xmax>1565</xmax>
			<ymax>494</ymax>
		</bndbox>
	</object>
	<object>
		<name>ship</name>
		<flag>rectangle</flag>
		<pose>Unspecified</pose>
		<truncated>0</truncated>
		<difficult>0</difficult>
		<bndbox>
			<xmin>27</xmin>
			<ymin>922</ymin>
			<xmax>99</xmax>
			<ymax>946</ymax>
		</bndbox>
	</object>
	<object>
		<name>ship</name>
		<flag>rectangle</flag>
		<pose>Unspecified</pose>
		<truncated>0</truncated>
		<difficult>0</difficult>
		<bndbox>
			<xmin>1387</xmin>
			<ymin>1057</ymin>
			<xmax>1521</xmax>
			<ymax>1080</ymax>
		</bndbox>
	</object>
	<object>
		<name>ship</name>
		<flag>rectangle</flag>
		<pose>Unspecified</pose>
		<truncated>0</truncated>
		<difficult>0</difficult>
		<bndbox>
			<xmin>1543</xmin>
			<ymin>991</ymin>
			<xmax>1684</xmax>
			<ymax>1027</ymax>
		</bndbox>
	</object>
	<object>
		<name>ship</name>
		<flag>rectangle</flag>
		<pose>Unspecified</pose>
		<truncated>0</truncated>
		<difficult>0</difficult>
		<bndbox>
			<xmin>461</xmin>
			<ymin>910</ymin>
			<xmax>565</xmax>
			<ymax>937</ymax>
		</bndbox>
	</object>
	<object>
		<name>ship</name>
		<flag>rectangle</flag>
		<pose>Unspecified</pose>
		<truncated>0</truncated>
		<difficult>0</difficult>
		<bndbox>
			<xmin>1731</xmin>
			<ymin>612</ymin>
			<xmax>1919</xmax>
			<ymax>643</ymax>
		</bndbox>
	</object>
	<object>
		<name>ship</name>
		<flag>rectangle</flag>
		<pose>Unspecified</pose>
		<truncated>0</truncated>
		<difficult>0</difficult>
		<bndbox>
			<xmin>1121</xmin>
			<ymin>740</ymin>
			<xmax>1470</xmax>
			<ymax>837</ymax>
		</bndbox>
	</object>
	<object>
		<name>ship</name>
		<flag>rectangle</flag>
		<pose>Unspecified</pose>
		<truncated>0</truncated>
		<difficult>0</difficult>
		<bndbox>
			<xmin>732</xmin>
			<ymin>879</ymin>
			<xmax>880</xmax>
			<ymax>916</ymax>
		</bndbox>
	</object>
	<object>
		<name>ship</name>
		<flag>rectangle</flag>
		<pose>Unspecified</pose>
		<truncated>0</truncated>
		<difficult>0</difficult>
		<bndbox>
			<xmin>382</xmin>
			<ymin>507</ymin>
			<xmax>507</xmax>
			<ymax>541</ymax>
		</bndbox>
	</object>
	<object>
		<name>ship</name>
		<flag>rectangle</flag>
		<pose>Unspecified</pose>
		<truncated>0</truncated>
		<difficult>0</difficult>
		<bndbox>
			<xmin>702</xmin>
			<ymin>1004</ymin>
			<xmax>848</xmax>
			<ymax>1042</ymax>
		</bndbox>
	</object>
	<object>
		<name>ship</name>
		<flag>rectangle</flag>
		<pose>Unspecified</pose>
		<truncated>0</truncated>
		<difficult>0</difficult>
		<bndbox>
			<xmin>938</xmin>
			<ymin>964</ymin>
			<xmax>1056</xmax>
			<ymax>1006</ymax>
		</bndbox>
	</object>
	<object>
		<name>ship</name>
		<flag>rectangle</flag>
		<pose>Unspecified</pose>
		<truncated>0</truncated>
		<difficult>0</difficult>
		<bndbox>
			<xmin>426</xmin>
			<ymin>605</ymin>
			<xmax>651</xmax>
			<ymax>674</ymax>
		</bndbox>
	</object>
</annotation>
