<?xml version='1.0' encoding='utf-8'?>
<annotation verified="no">
	<folder>./JPEGImages</folder>
	<filename>893</filename>
	<path>./JPEGImages\893.jpg</path>
	<checked>NO</checked>
	<source>
		<database>Unknown</database>
	</source>
	<size>
		<width>1920</width>
		<height>1080</height>
		<depth>3</depth>
	</size>
	<segmented>0</segmented>
	<object>
		<name>ship</name>
		<flag>rectangle</flag>
		<pose>Unspecified</pose>
		<truncated>0</truncated>
		<difficult>0</difficult>
		<bndbox>
			<xmin>0</xmin>
			<ymin>687</ymin>
			<xmax>33</xmax>
			<ymax>734</ymax>
		</bndbox>
	</object>
	<object>
		<name>ship</name>
		<flag>rectangle</flag>
		<pose>Unspecified</pose>
		<truncated>0</truncated>
		<difficult>0</difficult>
		<bndbox>
			<xmin>70</xmin>
			<ymin>467</ymin>
			<xmax>110</xmax>
			<ymax>479</ymax>
		</bndbox>
	</object>
	<object>
		<name>ship</name>
		<flag>rectangle</flag>
		<pose>Unspecified</pose>
		<truncated>0</truncated>
		<difficult>0</difficult>
		<bndbox>
			<xmin>1377</xmin>
			<ymin>1062</ymin>
			<xmax>1486</xmax>
			<ymax>1080</ymax>
		</bndbox>
	</object>
	<object>
		<name>ship</name>
		<flag>rectangle</flag>
		<pose>Unspecified</pose>
		<truncated>0</truncated>
		<difficult>0</difficult>
		<bndbox>
			<xmin>1505</xmin>
			<ymin>487</ymin>
			<xmax>1561</xmax>
			<ymax>497</ymax>
		</bndbox>
	</object>
	<object>
		<name>ship</name>
		<flag>rectangle</flag>
		<pose>Unspecified</pose>
		<truncated>0</truncated>
		<difficult>0</difficult>
		<bndbox>
			<xmin>19</xmin>
			<ymin>925</ymin>
			<xmax>94</xmax>
			<ymax>950</ymax>
		</bndbox>
	</object>
	<object>
		<name>ship</name>
		<flag>rectangle</flag>
		<pose>Unspecified</pose>
		<truncated>0</truncated>
		<difficult>0</difficult>
		<bndbox>
			<xmin>1722</xmin>
			<ymin>611</ymin>
			<xmax>1918</xmax>
			<ymax>646</ymax>
		</bndbox>
	</object>
	<object>
		<name>ship</name>
		<flag>rectangle</flag>
		<pose>Unspecified</pose>
		<truncated>0</truncated>
		<difficult>0</difficult>
		<bndbox>
			<xmin>376</xmin>
			<ymin>508</ymin>
			<xmax>502</xmax>
			<ymax>541</ymax>
		</bndbox>
	</object>
	<object>
		<name>ship</name>
		<flag>rectangle</flag>
		<pose>Unspecified</pose>
		<truncated>0</truncated>
		<difficult>0</difficult>
		<bndbox>
			<xmin>697</xmin>
			<ymin>1010</ymin>
			<xmax>841</xmax>
			<ymax>1047</ymax>
		</bndbox>
	</object>
	<object>
		<name>ship</name>
		<flag>rectangle</flag>
		<pose>Unspecified</pose>
		<truncated>0</truncated>
		<difficult>0</difficult>
		<bndbox>
			<xmin>1535</xmin>
			<ymin>996</ymin>
			<xmax>1677</xmax>
			<ymax>1033</ymax>
		</bndbox>
	</object>
	<object>
		<name>ship</name>
		<flag>rectangle</flag>
		<pose>Unspecified</pose>
		<truncated>0</truncated>
		<difficult>0</difficult>
		<bndbox>
			<xmin>455</xmin>
			<ymin>913</ymin>
			<xmax>561</xmax>
			<ymax>941</ymax>
		</bndbox>
	</object>
	<object>
		<name>ship</name>
		<flag>rectangle</flag>
		<pose>Unspecified</pose>
		<truncated>0</truncated>
		<difficult>0</difficult>
		<bndbox>
			<xmin>727</xmin>
			<ymin>883</ymin>
			<xmax>877</xmax>
			<ymax>921</ymax>
		</bndbox>
	</object>
	<object>
		<name>ship</name>
		<flag>rectangle</flag>
		<pose>Unspecified</pose>
		<truncated>0</truncated>
		<difficult>0</difficult>
		<bndbox>
			<xmin>1117</xmin>
			<ymin>744</ymin>
			<xmax>1464</xmax>
			<ymax>840</ymax>
		</bndbox>
	</object>
	<object>
		<name>ship</name>
		<flag>rectangle</flag>
		<pose>Unspecified</pose>
		<truncated>0</truncated>
		<difficult>0</difficult>
		<bndbox>
			<xmin>932</xmin>
			<ymin>970</ymin>
			<xmax>1047</xmax>
			<ymax>1011</ymax>
		</bndbox>
	</object>
	<object>
		<name>ship</name>
		<flag>rectangle</flag>
		<pose>Unspecified</pose>
		<truncated>0</truncated>
		<difficult>0</difficult>
		<bndbox>
			<xmin>420</xmin>
			<ymin>606</ymin>
			<xmax>647</xmax>
			<ymax>674</ymax>
		</bndbox>
	</object>
</annotation>
